google_custom_search/__init__.py
google_custom_search/adapter.py
google_custom_search/enums.py
google_custom_search/errors.py
google_custom_search/py.typed
google_custom_search/search.py
google_custom_search/types.py
google_custom_search-3.0.0.dist-info/LICENSE
google_custom_search-3.0.0.dist-info/METADATA
google_custom_search-3.0.0.dist-info/WHEEL
google_custom_search-3.0.0.dist-info/top_level.txt
google_custom_search-3.0.0.dist-info/RECORD
