Metadata-Version: 2.1
Name: google-custom-search
Version: 3.0.0
Summary: This is for google custom search api.
Home-page: https://github.com/mc-fdc-dev/google-custom-search
Author: mc-fdc-dev
Author-email: masato190411@gmail.com
Classifier: Programming Language :: Python :: 3.8
Classifier: Programming Language :: Python :: 3.9
Classifier: Programming Language :: Python :: 3.10
Classifier: Programming Language :: Python :: 3.11
Classifier: Programming Language :: Python :: 3.12
Classifier: Programming Language :: Python :: 3.13
Classifier: License :: OSI Approved :: MIT License
Classifier: Operating System :: OS Independent
License-File: LICENSE
Requires-Dist: requests>=2.27.1
Provides-Extra: async
Requires-Dist: aiohttp>=3.8.1; extra == "async"
